{
  "pages": {
    "admin-collections": {
      "path": "/admin/collections",
      "auth": true
    },
    "admin-collections-collection": {
      "path": "/admin/collections/new/",
      "auth": true
    },
    "admin-collections-collection-edit": {
      "path": "/admin/collections/:id/",
      "auth": true
    }
  },
  "extensions": {
    "admin-collections": {
      "component": "ListPageContainer"
    },
    "admin-collections-collection": {
      "component": "CollectionContainer"
    },
    "admin-collections-collection-edit": {
      "component": "CollectionContainer"
    }
  }
}
